{
  "best_model": "MLP Neural Network",
  "accuracy": 0.9724371373307543,
  "cv_score": 0.9724371373307543,
  "timestamp": "2026-04-05T15:53:18.839036",
  "num_classes": 27,
  "classes": [
    "account_help",
    "analytics",
    "bot_identity",
    "category_search",
    "chatbot_rating",
    "complaint",
    "contact_support",
    "delivery_time",
    "discount_promo",
    "goodbye",
    "greeting",
    "invoice",
    "order_cancel",
    "order_history",
    "order_track",
    "payment_methods",
    "place_order",
    "product_price",
    "product_search",
    "recommendation",
    "return_policy",
    "shipping_fee",
    "stock_check",
    "stock_notification",
    "support_ticket",
    "thanks",
    "warranty"
  ]
}